aicapture/__init__.py
aicapture/cache.py
aicapture/content_cleaner.py
aicapture/settings.py
aicapture/utils.py
aicapture/vid_capture.py
aicapture/vision_capture.py
aicapture/vision_models.py
aicapture/vision_parser.py
aicapture-0.3.7.dist-info/METADATA
aicapture-0.3.7.dist-info/WHEEL
aicapture-0.3.7.dist-info/licenses/LICENSE
aicapture-0.3.7.dist-info/RECORD
