Metadata-Version: 2.4
Name: aicapture
Version: 0.3.7
Summary: A Python module to capture knowledge from documents using Vision Language Models (VLMs)
Project-URL: Homepage, https://github.com/Aitomatic/ai-vision-capture
Project-URL: Repository, https://github.com/Aitomatic/ai-vision-capture
Project-URL: Issues, https://github.com/Aitomatic/ai-vision-capture/issues
Author: Aitomatic
License: MIT
License-File: LICENSE
Keywords: ai,capture,document,language,models,vision,vlm
Classifier: Development Status :: 4 - Beta
Classifier: Intended Audience :: Developers
Classifier: License :: OSI Approved :: MIT License
Classifier: Programming Language :: Python :: 3
Classifier: Programming Language :: Python :: 3.10
Classifier: Programming Language :: Python :: 3.11
Classifier: Programming Language :: Python :: 3.12
Requires-Python: >=3.10
Requires-Dist: anthropic>=0.30.1
Requires-Dist: boto3>=1.34.0
Requires-Dist: loguru>=0.7.3
Requires-Dist: numpy>=2.2.3
Requires-Dist: openai>=1.107.0
Requires-Dist: opencv-python>=4.11.0.86
Requires-Dist: pillow>=11.1.0
Requires-Dist: pymupdf>=1.25.3
Requires-Dist: python-dotenv>=1.0.1
Provides-Extra: aws
Requires-Dist: boto3>=1.34.0; extra == 'aws'
Provides-Extra: azure
Requires-Dist: azure-cognitiveservices-vision-computervision; extra == 'azure'
Provides-Extra: dev
Requires-Dist: mypy>=1.8.0; extra == 'dev'
Requires-Dist: pre-commit>=3.6.0; extra == 'dev'
Requires-Dist: pytest-asyncio>=0.23.5; extra == 'dev'
Requires-Dist: pytest-cov>=4.1.0; extra == 'dev'
Requires-Dist: pytest>=8.0.0; extra == 'dev'
Requires-Dist: ruff>=0.8.0; extra == 'dev'
Provides-Extra: google
Requires-Dist: google-cloud-vision; extra == 'google'
